fdn_kg_loader/__init__.py
fdn_kg_loader/filter.py
fdn_kg_loader/loader.py
fdn_kg_loader/model.py
fdn_kg_loader/store.py
fdn_kg_loader/model/__init__.py
fdn_kg_loader/store/__init__.py
fdn_kg_loader/tests/__init__.py
fdn_kg_loader/tests/test_brand.py
fdn_kg_loader/tests/test_insert.py
fdn_kg_loader/tests/test_product.py
fdnloader/__init__.py
fdnloader/filter.py
fdnloader/loader.py
fdnloader/model/__init__.py
fdnloader/store/__init__.py
fdn_kg_loader-0.14.3.dist-info/METADATA
fdn_kg_loader-0.14.3.dist-info/WHEEL
fdn_kg_loader-0.14.3.dist-info/entry_points.txt
fdn_kg_loader-0.14.3.dist-info/top_level.txt
fdn_kg_loader-0.14.3.dist-info/RECORD
