Metadata-Version: 2.1
Name: fdn-kg-loader
Version: 0.14.3
Summary: UNKNOWN
Home-page: UNKNOWN
Author: UNKNOWN
Author-email: UNKNOWN
License: Restricted License, FDN license
Platform: UNKNOWN
Requires-Dist: pandas
Requires-Dist: grpcio
Requires-Dist: protobuf
Requires-Dist: grakn
Requires-Dist: grakn-client
Requires-Dist: click
Requires-Dist: six
